ddd_shared_domain/entity.py
ddd_shared_domain-0.1.0.1.dist-info/METADATA
ddd_shared_domain-0.1.0.1.dist-info/WHEEL
ddd_shared_domain-0.1.0.1.dist-info/top_level.txt
ddd_shared_domain-0.1.0.1.dist-info/RECORD
