Metadata-Version: 2.4
Name: ddd-shared-domain
Version: 0.1.0.1
Summary: Add your description here
Requires-Python: >=3.10
Requires-Dist: ddd-value-objects==0.1.7.1
